{
  "login": "LeonardoFurtado",
  "id": 22118060,
  "node_id": "MDQ6VXNlcjIyMTE4MDYw",
  "avatar_url": "https://avatars3.githubusercontent.com/u/22118060?v=4",
  "gravatar_id": "",
  "url": "https://api.github.com/users/LeonardoFurtado",
  "html_url": "https://github.com/LeonardoFurtado",
  "followers_url": "https://api.github.com/users/LeonardoFurtado/followers",
  "following_url": "https://api.github.com/users/LeonardoFurtado/following{/other_user}",
  "gists_url": "https://api.github.com/users/LeonardoFurtado/gists{/gist_id}",
  "starred_url": "https://api.github.com/users/LeonardoFurtado/starred{/owner}{/repo}",
  "subscriptions_url": "https://api.github.com/users/LeonardoFurtado/subscriptions",
  "organizations_url": "https://api.github.com/users/LeonardoFurtado/orgs",
  "repos_url": "https://api.github.com/users/LeonardoFurtado/repos",
  "events_url": "https://api.github.com/users/LeonardoFurtado/events{/privacy}",
  "received_events_url": "https://api.github.com/users/LeonardoFurtado/received_events",
  "type": "User",
  "site_admin": false,
  "name": "Leonardo Furtado",
  "company": "Federal University of Pará",
  "blog": "",
  "location": "Brazil",
  "email": null,
  "hireable": null,
  "bio": "Computer Science Student :computer: Python enthusiast :snake: interested in becoming a Software Engineering Researcher :shipit:",
  "public_repos": 23,
  "public_gists": 1,
  "followers": 16,
  "following": 60,
  "created_at": "2016-09-10T14:30:58Z",
  "updated_at": "2019-05-18T13:06:07Z"
}